flake8_internal_name_import.py
flake8_internal_name_import-1.0.1.dist-info/LICENSE
flake8_internal_name_import-1.0.1.dist-info/METADATA
flake8_internal_name_import-1.0.1.dist-info/WHEEL
flake8_internal_name_import-1.0.1.dist-info/entry_points.txt
flake8_internal_name_import-1.0.1.dist-info/top_level.txt
flake8_internal_name_import-1.0.1.dist-info/RECORD
