Metadata-Version: 2.1
Name: flake8-internal-name-import
Version: 1.0.1
Summary: flake8 plugin that reports imports of internal names
Home-page: https://github.com/rows-s/flake8_internal_name_import
Author: Vladimir Marmuz
Author-email: vladimir.rows@gmail.com
License: MIT
Keywords: python pep8 flake8 internal import
Classifier: Development Status :: 5 - Production/Stable
Classifier: Environment :: Console
Classifier: Framework :: Flake8
Classifier: Intended Audience :: Developers
Classifier: License :: OSI Approved :: GNU General Public License v2 (GPLv2)
Classifier: Operating System :: OS Independent
Classifier: Programming Language :: Python
Classifier: Programming Language :: Python :: 3
Classifier: Programming Language :: Python :: 3 :: Only
Classifier: Programming Language :: Python :: 3.7
Classifier: Programming Language :: Python :: 3.8
Classifier: Programming Language :: Python :: 3.9
Classifier: Programming Language :: Python :: 3.10
Classifier: Programming Language :: Python :: 3.11
Classifier: Programming Language :: Python :: Implementation :: CPython
Classifier: Topic :: Software Development
Classifier: Topic :: Software Development :: Quality Assurance
Requires-Python: >=3.7
License-File: LICENSE
Requires-Dist: flake8 >=3.3.0
Provides-Extra: test
Requires-Dist: pytest ; extra == 'test'
